fileslib/__init__.py
fileslib/core.py
fileslib-0.1.0.dist-info/licenses/LICENSE
fileslib-0.1.0.dist-info/METADATA
fileslib-0.1.0.dist-info/WHEEL
fileslib-0.1.0.dist-info/top_level.txt
fileslib-0.1.0.dist-info/RECORD
