Metadata-Version: 2.4
Name: fileslib
Version: 0.1.0
Summary: Creating, Reading, Editing, and Executing files.
Author: Aiden
